bqutils/__init__.py
bqutils/__main__.py
bqutils/bigquery_description_manager.py
bq_utils-0.1.1.dist-info/LICENSE
bq_utils-0.1.1.dist-info/METADATA
bq_utils-0.1.1.dist-info/WHEEL
bq_utils-0.1.1.dist-info/entry_points.txt
bq_utils-0.1.1.dist-info/top_level.txt
bq_utils-0.1.1.dist-info/RECORD
