Metadata-Version: 2.1
Name: bq-utils
Version: 0.1.1
Summary: A collection of BigQuery utilities
Home-page: https://github.com/matepaavo/bq-utils
Author: Balázs Máté
Author-email: matepaavo@gmail.com
License: MIT
Platform: UNKNOWN
Classifier: License :: OSI Approved :: MIT License
Classifier: Programming Language :: Python :: 3
Classifier: Programming Language :: Python :: 3.5
Requires-Dist: google-cloud-bigquery
